Pygments23ZhongwenWendang/README.md
Pygments23ZhongwenWendang/__init__.py
Pygments23ZhongwenWendang/__main__.py
Pygments23ZhongwenWendang/file.epub
Pygments23ZhongwenWendang/index.html
Pygments23ZhongwenWendang/css/__init__.py
Pygments23ZhongwenWendang/css/annotations.css
Pygments23ZhongwenWendang/css/main.css
Pygments23ZhongwenWendang/css/normalize.css
Pygments23ZhongwenWendang/css/popup.css
Pygments23ZhongwenWendang/font/__init__.py
Pygments23ZhongwenWendang/font/fontello.eot
Pygments23ZhongwenWendang/font/fontello.svg
Pygments23ZhongwenWendang/font/fontello.ttf
Pygments23ZhongwenWendang/font/fontello.woff
Pygments23ZhongwenWendang/img/__init__.py
Pygments23ZhongwenWendang/img/annotator-glyph-sprite.png
Pygments23ZhongwenWendang/img/annotator-icon-sprite.png
Pygments23ZhongwenWendang/img/apple-touch-icon.png
Pygments23ZhongwenWendang/img/cancelfullscreen.png
Pygments23ZhongwenWendang/img/close.png
Pygments23ZhongwenWendang/img/fullscreen.png
Pygments23ZhongwenWendang/img/loader.gif
Pygments23ZhongwenWendang/img/menu-icon.png
Pygments23ZhongwenWendang/img/save.png
Pygments23ZhongwenWendang/img/saved.png
Pygments23ZhongwenWendang/img/settings-s.png
Pygments23ZhongwenWendang/img/settings.png
Pygments23ZhongwenWendang/img/star.png
Pygments23ZhongwenWendang/js/__init__.py
Pygments23ZhongwenWendang/js/epub.js
Pygments23ZhongwenWendang/js/epub.min.js
Pygments23ZhongwenWendang/js/epub.min.map
Pygments23ZhongwenWendang/js/hooks.min.js
Pygments23ZhongwenWendang/js/hooks.min.map
Pygments23ZhongwenWendang/js/reader.js
Pygments23ZhongwenWendang/js/reader.js.map
Pygments23ZhongwenWendang/js/reader.min.js
Pygments23ZhongwenWendang/js/reader.min.map
Pygments23ZhongwenWendang/js/hooks/__init__.py
Pygments23ZhongwenWendang/js/hooks/extensions/__init__.py
Pygments23ZhongwenWendang/js/hooks/extensions/highlight.js
Pygments23ZhongwenWendang/js/libs/__init__.py
Pygments23ZhongwenWendang/js/libs/jquery.min.js
Pygments23ZhongwenWendang/js/libs/localforage.min.js
pygments_2_3_zhongwen_wendang-2024.3.4.0.dist-info/METADATA
pygments_2_3_zhongwen_wendang-2024.3.4.0.dist-info/WHEEL
pygments_2_3_zhongwen_wendang-2024.3.4.0.dist-info/entry_points.txt
pygments_2_3_zhongwen_wendang-2024.3.4.0.dist-info/top_level.txt
pygments_2_3_zhongwen_wendang-2024.3.4.0.dist-info/RECORD
